quickopt/annealing.cpython-39-darwin.so
quickopt/bayesopt_tpe.cpython-39-darwin.so
quickopt/common.cpython-39-darwin.so
quickopt/genetic.cpython-39-darwin.so
quickopt/pso.cpython-39-darwin.so
quickopt-0.1.8.dist-info/LICENSE
quickopt-0.1.8.dist-info/METADATA
quickopt-0.1.8.dist-info/WHEEL
quickopt-0.1.8.dist-info/top_level.txt
quickopt-0.1.8.dist-info/RECORD
