Metadata-Version: 2.1
Name: quickopt
Version: 0.1.8
Summary: A Python optimization toolkit focused on global optimization problems, featuring simple and customizable setup of various optimization algorithms implemented in C++.
Author: Varun Piram
Author-email: varunpiram@gmail.com
License-File: LICENSE
Requires-Dist: pybind11 (>=2.5.0)
